{"cameraMode":{"drawMode":0,"name":"Shaded","section":"Shading Mode"},"sceneLighting":true,"audioPlay":false,"sceneViewState":{"showFog":true,"showMaterialUpdate":false,"showSkybox":true,"showFlares":true,"showImageEffects":true,"showParticleSystems":true},"in2DMode":false,"pivot":{"x":-4.348017692565918,"y":-1.112358570098877,"z":-4.9932756423950199},"rotation":{"x":-0.05233883857727051,"y":0.9310349822044373,"z":-0.147862508893013,"w":-0.32955285906791689},"size":8.30208969116211,"orthographic":false}